rubpy/__init__.py
rubpy/rubika.py
rubpy/connections/__init__.py
rubpy/connections/requests.py
rubpy/connections/websocket.py
rubpy/encryption/__init__.py
rubpy/exceptions/__init__.py
rubpy/tools/__init__.py
evatygram-4.6.5.dist-info/METADATA
evatygram-4.6.5.dist-info/WHEEL
evatygram-4.6.5.dist-info/top_level.txt
evatygram-4.6.5.dist-info/RECORD
