Metadata-Version: 2.4
Name: evatygram
Version: 4.6.5
Summary: This is an unofficial library and fastest library for deploying robots on Rubika accounts.
Home-page: https://github.com/snipe4kill/rubika/
Author: Shayan Heidari
Author-email: snipe4kill@yahoo.com
Keywords: rubika,evatygram,rubikaio,chat,bot,robot,asyncio
Classifier: Programming Language :: Python :: 3.8
Classifier: Programming Language :: Python :: 3.9
Classifier: Programming Language :: Python :: 3.10
Classifier: Programming Language :: Python :: 3.11
Classifier: License :: OSI Approved :: MIT License
Classifier: Topic :: Internet
Classifier: Topic :: Communications
Classifier: Topic :: Communications :: Chat
Classifier: Topic :: Software Development :: Libraries
Classifier: Topic :: Software Development :: Libraries :: Python Modules
Classifier: Topic :: Software Development :: Libraries :: Application Frameworks
Requires-Python: ~=3.8
Requires-Dist: wheel
Requires-Dist: pycryptodome
Requires-Dist: websockets
Requires-Dist: ujson
Requires-Dist: pybase64
Requires-Dist: urllib3
Requires-Dist: mutagen
Requires-Dist: TinyTag
Dynamic: author
Dynamic: author-email
Dynamic: classifier
Dynamic: description
Dynamic: description-content-type
Dynamic: home-page
Dynamic: keywords
Dynamic: requires-dist
Dynamic: requires-python
Dynamic: summary
